[
  {
    "name": "Dr Abul Kalam Azad",
    "des": "Chairman & Principal",
    "img": "https://i.ibb.co/qd37zY4/kalam.jpg"
  },
  {
    "name": "Muhammad Rashid Al Majid Khan Siddiqi Mamun",
    "des": "Director",
    "img": "https://i.ibb.co/Z6PLWL5/mamun.jpg"
  },
  {
    "name": "Dr Fazal Mahmood",
    "des": "Director",
    "img": "https://i.ibb.co/VL3RPBF/fazal.jpg"
  },
  {
    "name": "Md. Shahadat Hossain ",
    "des": "Director",
    "img": "https://i.ibb.co/pRYVLYn/shahdat.jpg"
  }
]

